Workbook

Sheet Sheet

Sheet 가정
A1: DCF 분석 주요 가정
A3: [ 매출 가정 ]
A4: 기준연도 매출액(억원) | B4: 10000
A5: 1차년도 성장률 | B5: 0.15
A6: 2차년도 성장률 | B6: 0.12
A7: 3차년도 성장률 | B7: 0.1
A8: 4차년도 성장률 | B8: 0.08
A9: 5차년도 성장률 | B9: 0.06
A11: [ 비용 가정 ]
A12: EBITDA 마진 | B12: 0.2
A13: 감가상각비/매출 비율 | B13: 0.05
A14: CAPEX/매출 비율 | B14: 0.07
A15: 순운전자본 증감/매출 비율 | B15: 0.03
A16: 법인세율 | B16: 0.24
A18: [ 할인율 가정 ]
A19: WACC (가중평균자본비용) | B19: 0.1
A20: 영구성장률 | B20: 0.02
A22: [ 기타 ]
A23: 순차입금(억원) | B23: 5000
A24: 발행주식수(만주) | B24: 5000

Sheet DCF모델
A1: DCF 기업가치 분석 모델
A3: (단위: 억원) | B3: 기준년도 | C3: 1차년도 | D3: 2차년도 | E3: 3차년도 | F3: 4차년도 | G3: 5차년도
B4: 2025 | C4: 2026 | D4: 2027 | E4: 2028 | F4: 2029 | G4: 2030
A6: [ 매출 및 손익 추정 ]
A7: 매출액 | B7: =='가정'!B4 | C7: ==B7*(1+'가정'!B5) | D7: ==C7*(1+'가정'!B6) | E7: ==D7*(1+'가정'!B7) | F7: ==E7*(1+'가정'!B8) | G7: ==F7*(1+'가정'!B9)
A8: 매출성장률 | B8: - | C8: =='가정'!B5 | D8: =='가정'!B6 | E8: =='가정'!B7 | F8: =='가정'!B8 | G8: =='가정'!B9
A9: EBITDA | B9: ==B7*'가정'!B12 | C9: ==C7*'가정'!B12 | D9: ==D7*'가정'!B12 | E9: ==E7*'가정'!B12 | F9: ==F7*'가정'!B12 | G9: ==G7*'가정'!B12
A10: EBITDA 마진 | B10: =='가정'!B12 | C10: =='가정'!B12 | D10: =='가정'!B12 | E10: =='가정'!B12 | F10: =='가정'!B12 | G10: =='가정'!B12
A11: 감가상각비(D&A) | B11: ==B7*'가정'!B13 | C11: ==C7*'가정'!B13 | D11: ==D7*'가정'!B13 | E11: ==E7*'가정'!B13 | F11: ==F7*'가정'!B13 | G11: ==G7*'가정'!B13
A12: EBIT (영업이익) | B12: ==B9-B11 | C12: ==C9-C11 | D12: ==D9-D11 | E12: ==E9-E11 | F12: ==F9-F11 | G12: ==G9-G11
A13: 법인세 | B13: ==B12*'가정'!B16 | C13: ==C12*'가정'!B16 | D13: ==D12*'가정'!B16 | E13: ==E12*'가정'!B16 | F13: ==F12*'가정'!B16 | G13: ==G12*'가정'!B16
A14: NOPAT | B14: ==B12-B13 | C14: ==C12-C13 | D14: ==D12-D13 | E14: ==E12-E13 | F14: ==F12-F13 | G14: ==G12-G13
A16: [ 잉여현금흐름(FCF) 산출 ]
A17: NOPAT | B17: ==B14 | C17: ==C14 | D17: ==D14 | E17: ==E14 | F17: ==F14 | G17: ==G14
A18: (+) 감가상각비 | B18: ==B11 | C18: ==C11 | D18: ==D11 | E18: ==E11 | F18: ==F11 | G18: ==G11
A19: (-) CAPEX | B19: ==B7*'가정'!B14 | C19: ==C7*'가정'!B14 | D19: ==D7*'가정'!B14 | E19: ==E7*'가정'!B14 | F19: ==F7*'가정'!B14 | G19: ==G7*'가정'!B14
A20: (-) 순운전자본 증감 | B20: 0 | C20: ==(C7-B7)*'가정'!B15 | D20: ==(D7-C7)*'가정'!B15 | E20: ==(E7-D7)*'가정'!B15 | F20: ==(F7-E7)*'가정'!B15 | G20: ==(G7-F7)*'가정'!B15
A21: 잉여현금흐름(FCF) | B21: ==B17+B18-B19-B20 | C21: ==C17+C18-C19-C20 | D21: ==D17+D18-D19-D20 | E21: ==E17+E18-E19-E20 | F21: ==F17+F18-F19-F20 | G21: ==G17+G18-G19-G20
A23: [ 현재가치 및 기업가치 ]
A24: WACC | B24: =='가정'!B19
A25: 할인계수 | C25: ==1/(1+$B$24)^1 | D25: ==1/(1+$B$24)^2 | E25: ==1/(1+$B$24)^3 | F25: ==1/(1+$B$24)^4 | G25: ==1/(1+$B$24)^5
A26: FCF 현재가치 | C26: ==C21*C25 | D26: ==D21*D25 | E26: ==E21*E25 | F26: ==F21*F25 | G26: ==G21*G25
A28: 영구성장률 | B28: =='가정'!B20
A29: 터미널밸류(TV) | B29: ==G21*(1+B28)/(B24-B28)
A30: TV 현재가치 | B30: ==B29*G25
A32: FCF 현재가치 합계 | B32: ==SUM(C26:G26)
A33: TV 현재가치 | B33: ==B30
A34: 기업가치(EV) | B34: ==B32+B33
A36: [ 주주가치 산출 ]
A37: 기업가치(EV) | B37: ==B34
A38: (-) 순차입금 | B38: =='가정'!B23
A39: 주주가치(Equity Value) | B39: ==B37-B38
A40: 발행주식수(만주) | B40: =='가정'!B24
A41: 주당 적정가치(원) | B41: ==B39/B40*10000

Sheet 민감도분석
A1: DCF 민감도 분석
A2: (주당 적정가치, 단위: 원)
A3: WACC \\ 성장률 | C3: 0 | D3: 0.01 | E3: 0.02 | F3: 0.03 | G3: 0.04
B4: 0.08 | C4: ==('DCF모델'!C21/(1+$B4)+'DCF모델'!D21/(1+$B4)^2+'DCF모델'!E21/(1+$B4)^3+'DCF모델'!F21/(1+$B4)^4+'DCF모델'!G21/(1+$B4)^5+'DCF모델'!G21*(1+C$3)/($B4-C$3)/(1+$B4)^5-'가정'!$B$23)/'가정'!$B$24*10000 | D4: ==('DCF모델'!C21/(1+$B4)+'DCF모델'!D21/(1+$B4)^2+'DCF모델'!E21/(1+$B4)^3+'DCF모델'!F21/(1+$B4)^4+'DCF모델'!G21/(1+$B4)^5+'DCF모델'!G21*(1+D$3)/($B4-D$3)/(1+$B4)^5-'가정'!$B$23)/'가정'!$B$24*10000 | E4: ==('DCF모델'!C21/(1+$B4)+'DCF모델'!D21/(1+$B4)^2+'DCF모델'!E21/(1+$B4)^3+'DCF모델'!F21/(1+$B4)^4+'DCF모델'!G21/(1+$B4)^5+'DCF모델'!G21*(1+E$3)/($B4-E$3)/(1+$B4)^5-'가정'!$B$23)/'가정'!$B$24*10000 | F4: ==('DCF모델'!C21/(1+$B4)+'DCF모델'!D21/(1+$B4)^2+'DCF모델'!E21/(1+$B4)^3+'DCF모델'!F21/(1+$B4)^4+'DCF모델'!G21/(1+$B4)^5+'DCF모델'!G21*(1+F$3)/($B4-F$3)/(1+$B4)^5-'가정'!$B$23)/'가정'!$B$24*10000 | G4: ==('DCF모델'!C21/(1+$B4)+'DCF모델'!D21/(1+$B4)^2+'DCF모델'!E21/(1+$B4)^3+'DCF모델'!F21/(1+$B4)^4+'DCF모델'!G21/(1+$B4)^5+'DCF모델'!G21*(1+G$3)/($B4-G$3)/(1+$B4)^5-'가정'!$B$23)/'가정'!$B$24*10000
B5: 0.09 | C5: ==('DCF모델'!C21/(1+$B5)+'DCF모델'!D21/(1+$B5)^2+'DCF모델'!E21/(1+$B5)^3+'DCF모델'!F21/(1+$B5)^4+'DCF모델'!G21/(1+$B5)^5+'DCF모델'!G21*(1+C$3)/($B5-C$3)/(1+$B5)^5-'가정'!$B$23)/'가정'!$B$24*10000 | D5: ==('DCF모델'!C21/(1+$B5)+'DCF모델'!D21/(1+$B5)^2+'DCF모델'!E21/(1+$B5)^3+'DCF모델'!F21/(1+$B5)^4+'DCF모델'!G21/(1+$B5)^5+'DCF모델'!G21*(1+D$3)/($B5-D$3)/(1+$B5)^5-'가정'!$B$23)/'가정'!$B$24*10000 | E5: ==('DCF모델'!C21/(1+$B5)+'DCF모델'!D21/(1+$B5)^2+'DCF모델'!E21/(1+$B5)^3+'DCF모델'!F21/(1+$B5)^4+'DCF모델'!G21/(1+$B5)^5+'DCF모델'!G21*(1+E$3)/($B5-E$3)/(1+$B5)^5-'가정'!$B$23)/'가정'!$B$24*10000 | F5: ==('DCF모델'!C21/(1+$B5)+'DCF모델'!D21/(1+$B5)^2+'DCF모델'!E21/(1+$B5)^3+'DCF모델'!F21/(1+$B5)^4+'DCF모델'!G21/(1+$B5)^5+'DCF모델'!G21*(1+F$3)/($B5-F$3)/(1+$B5)^5-'가정'!$B$23)/'가정'!$B$24*10000 | G5: ==('DCF모델'!C21/(1+$B5)+'DCF모델'!D21/(1+$B5)^2+'DCF모델'!E21/(1+$B5)^3+'DCF모델'!F21/(1+$B5)^4+'DCF모델'!G21/(1+$B5)^5+'DCF모델'!G21*(1+G$3)/($B5-G$3)/(1+$B5)^5-'가정'!$B$23)/'가정'!$B$24*10000
A6: WACC | B6: 0.1 | C6: ==('DCF모델'!C21/(1+$B6)+'DCF모델'!D21/(1+$B6)^2+'DCF모델'!E21/(1+$B6)^3+'DCF모델'!F21/(1+$B6)^4+'DCF모델'!G21/(1+$B6)^5+'DCF모델'!G21*(1+C$3)/($B6-C$3)/(1+$B6)^5-'가정'!$B$23)/'가정'!$B$24*10000 | D6: ==('DCF모델'!C21/(1+$B6)+'DCF모델'!D21/(1+$B6)^2+'DCF모델'!E21/(1+$B6)^3+'DCF모델'!F21/(1+$B6)^4+'DCF모델'!G21/(1+$B6)^5+'DCF모델'!G21*(1+D$3)/($B6-D$3)/(1+$B6)^5-'가정'!$B$23)/'가정'!$B$24*10000 | E6: ==('DCF모델'!C21/(1+$B6)+'DCF모델'!D21/(1+$B6)^2+'DCF모델'!E21/(1+$B6)^3+'DCF모델'!F21/(1+$B6)^4+'DCF모델'!G21/(1+$B6)^5+'DCF모델'!G21*(1+E$3)/($B6-E$3)/(1+$B6)^5-'가정'!$B$23)/'가정'!$B$24*10000 | F6: ==('DCF모델'!C21/(1+$B6)+'DCF모델'!D21/(1+$B6)^2+'DCF모델'!E21/(1+$B6)^3+'DCF모델'!F21/(1+$B6)^4+'DCF모델'!G21/(1+$B6)^5+'DCF모델'!G21*(1+F$3)/($B6-F$3)/(1+$B6)^5-'가정'!$B$23)/'가정'!$B$24*10000 | G6: ==('DCF모델'!C21/(1+$B6)+'DCF모델'!D21/(1+$B6)^2+'DCF모델'!E21/(1+$B6)^3+'DCF모델'!F21/(1+$B6)^4+'DCF모델'!G21/(1+$B6)^5+'DCF모델'!G21*(1+G$3)/($B6-G$3)/(1+$B6)^5-'가정'!$B$23)/'가정'!$B$24*10000
B7: 0.11 | C7: ==('DCF모델'!C21/(1+$B7)+'DCF모델'!D21/(1+$B7)^2+'DCF모델'!E21/(1+$B7)^3+'DCF모델'!F21/(1+$B7)^4+'DCF모델'!G21/(1+$B7)^5+'DCF모델'!G21*(1+C$3)/($B7-C$3)/(1+$B7)^5-'가정'!$B$23)/'가정'!$B$24*10000 | D7: ==('DCF모델'!C21/(1+$B7)+'DCF모델'!D21/(1+$B7)^2+'DCF모델'!E21/(1+$B7)^3+'DCF모델'!F21/(1+$B7)^4+'DCF모델'!G21/(1+$B7)^5+'DCF모델'!G21*(1+D$3)/($B7-D$3)/(1+$B7)^5-'가정'!$B$23)/'가정'!$B$24*10000 | E7: ==('DCF모델'!C21/(1+$B7)+'DCF모델'!D21/(1+$B7)^2+'DCF모델'!E21/(1+$B7)^3+'DCF모델'!F21/(1+$B7)^4+'DCF모델'!G21/(1+$B7)^5+'DCF모델'!G21*(1+E$3)/($B7-E$3)/(1+$B7)^5-'가정'!$B$23)/'가정'!$B$24*10000 | F7: ==('DCF모델'!C21/(1+$B7)+'DCF모델'!D21/(1+$B7)^2+'DCF모델'!E21/(1+$B7)^3+'DCF모델'!F21/(1+$B7)^4+'DCF모델'!G21/(1+$B7)^5+'DCF모델'!G21*(1+F$3)/($B7-F$3)/(1+$B7)^5-'가정'!$B$23)/'가정'!$B$24*10000 | G7: ==('DCF모델'!C21/(1+$B7)+'DCF모델'!D21/(1+$B7)^2+'DCF모델'!E21/(1+$B7)^3+'DCF모델'!F21/(1+$B7)^4+'DCF모델'!G21/(1+$B7)^5+'DCF모델'!G21*(1+G$3)/($B7-G$3)/(1+$B7)^5-'가정'!$B$23)/'가정'!$B$24*10000
B8: 0.12 | C8: ==('DCF모델'!C21/(1+$B8)+'DCF모델'!D21/(1+$B8)^2+'DCF모델'!E21/(1+$B8)^3+'DCF모델'!F21/(1+$B8)^4+'DCF모델'!G21/(1+$B8)^5+'DCF모델'!G21*(1+C$3)/($B8-C$3)/(1+$B8)^5-'가정'!$B$23)/'가정'!$B$24*10000 | D8: ==('DCF모델'!C21/(1+$B8)+'DCF모델'!D21/(1+$B8)^2+'DCF모델'!E21/(1+$B8)^3+'DCF모델'!F21/(1+$B8)^4+'DCF모델'!G21/(1+$B8)^5+'DCF모델'!G21*(1+D$3)/($B8-D$3)/(1+$B8)^5-'가정'!$B$23)/'가정'!$B$24*10000 | E8: ==('DCF모델'!C21/(1+$B8)+'DCF모델'!D21/(1+$B8)^2+'DCF모델'!E21/(1+$B8)^3+'DCF모델'!F21/(1+$B8)^4+'DCF모델'!G21/(1+$B8)^5+'DCF모델'!G21*(1+E$3)/($B8-E$3)/(1+$B8)^5-'가정'!$B$23)/'가정'!$B$24*10000 | F8: ==('DCF모델'!C21/(1+$B8)+'DCF모델'!D21/(1+$B8)^2+'DCF모델'!E21/(1+$B8)^3+'DCF모델'!F21/(1+$B8)^4+'DCF모델'!G21/(1+$B8)^5+'DCF모델'!G21*(1+F$3)/($B8-F$3)/(1+$B8)^5-'가정'!$B$23)/'가정'!$B$24*10000 | G8: ==('DCF모델'!C21/(1+$B8)+'DCF모델'!D21/(1+$B8)^2+'DCF모델'!E21/(1+$B8)^3+'DCF모델'!F21/(1+$B8)^4+'DCF모델'!G21/(1+$B8)^5+'DCF모델'!G21*(1+G$3)/($B8-G$3)/(1+$B8)^5-'가정'!$B$23)/'가정'!$B$24*10000
